bottle_file_cache.py
bottle_file_cache-1.1.0.dist-info/METADATA
bottle_file_cache-1.1.0.dist-info/WHEEL
bottle_file_cache-1.1.0.dist-info/licenses/LICENSE
bottle_file_cache-1.1.0.dist-info/RECORD
