Metadata-Version: 2.4
Name: bottle-file-cache
Version: 1.1.0
Summary: A simple file cache for the Python Bottle web framework.
Project-URL: Homepage, https://pypi.org/project/bottle-file-cache
Project-URL: Changelog, https://github.com/BoboTiG/bottle-file-cache/blob/main/CHANGELOG.md
Project-URL: Source, https://github.com/BoboTiG/bottle-file-cache
Project-URL: Sponsor, https://github.com/sponsors/BoboTiG
Project-URL: Tracker, https://github.com/BoboTiG/bottle-file-cache/issues
Project-URL: Released Versions, https://github.com/BoboTiG/bottle-file-cache/releases
Author-email: Mickaël Schoentgen <contact@tiger-222.fr>
Maintainer-email: Mickaël Schoentgen <contact@tiger-222.fr>
License: MIT License
License-File: LICENSE
Keywords: bottle,cache,file
Classifier: Development Status :: 5 - Production/Stable
Classifier: Environment :: Console
Classifier: Intended Audience :: Developers
Classifier: License :: OSI Approved :: MIT License
Classifier: Programming Language :: Python
Classifier: Programming Language :: Python :: 3
Classifier: Programming Language :: Python :: 3 :: Only
Classifier: Programming Language :: Python :: 3.10
Classifier: Programming Language :: Python :: 3.11
Classifier: Programming Language :: Python :: 3.12
Classifier: Programming Language :: Python :: 3.13
Classifier: Programming Language :: Python :: 3.14
Classifier: Programming Language :: Python :: Implementation :: CPython
Classifier: Topic :: Software Development :: Libraries :: Python Modules
Requires-Python: >=3.10
Provides-Extra: dev
Requires-Dist: build==1.2.2.post1; extra == 'dev'
Requires-Dist: twine==6.1.0; extra == 'dev'
Provides-Extra: tests
Requires-Dist: bottle==0.13.3; extra == 'tests'
Requires-Dist: mypy==1.15.0; extra == 'tests'
Requires-Dist: pytest-cov==6.1.1; extra == 'tests'
Requires-Dist: pytest==8.3.5; extra == 'tests'
Requires-Dist: ruff==0.11.11; extra == 'tests'
Requires-Dist: webtest==3.0.4; extra == 'tests'
